voevent_parse-0.9.5.dist-info/WHEEL
voevent_parse-0.9.5.dist-info/RECORD
voevent_parse-0.9.5.dist-info/DESCRIPTION.rst
voevent_parse-0.9.5.dist-info/metadata.json
voevent_parse-0.9.5.dist-info/top_level.txt
voevent_parse-0.9.5.dist-info/METADATA
voeventparse/definitions.py
voeventparse/misc.py
voeventparse/_version.py
voeventparse/convenience.py
voeventparse/__init__.py
voeventparse/voevent.py
voeventparse/tests/test_examples.py
voeventparse/tests/test_voeventparse.py
voeventparse/tests/__init__.py
voeventparse/tests/resources/no_namespace_packet.xml
voeventparse/tests/resources/SWIFT_xrt_position_v1.1_example.xml
voeventparse/tests/resources/datapaths.py
voeventparse/tests/resources/MOA_Lensing_Event_2015-07-10T14:50:54.00.xml
voeventparse/tests/resources/SWIFT_bat_position_v2.0_example.xml
voeventparse/tests/resources/__init__.py
