Metadata-Version: 2.0
Name: voevent-parse
Version: 0.9.5
Summary: Convenience routines for parsing and manipulation of VOEvent XML packets.
Home-page: https://github.com/timstaley/voevent-parse
Author: Tim Staley
Author-email: timstaley337@gmail.com
License: UNKNOWN
Platform: UNKNOWN
Requires-Dist: lxml (<4.0,>=2.3)
Requires-Dist: six
Requires-Dist: iso8601
